celldect/__init__.py
celldect/celldect20.cp310-win_amd64.pyd
celldect/celldect20.cpython-310-x86_64-linux-gnu.so
celldect/celldect30.cp310-win_amd64.pyd
celldect/celldect30.cpython-310-x86_64-linux-gnu.so
celldect-0.1.6.dist-info/METADATA
celldect-0.1.6.dist-info/WHEEL
celldect-0.1.6.dist-info/top_level.txt
celldect-0.1.6.dist-info/RECORD
