Metadata-Version: 2.4
Name: celldect
Version: 0.1.6
Summary: A cell image process Python package
Author: cellman
Author-email: cellman80@163.com
Classifier: Programming Language :: Python :: 3.10
Classifier: Operating System :: Microsoft :: Windows
Classifier: Operating System :: POSIX :: Linux
Requires-Python: >=3.10
Dynamic: author
Dynamic: author-email
Dynamic: classifier
Dynamic: requires-python
Dynamic: summary
